{"altitude": 0.0, "latitude": 44.8762702942, "longitude": 11.933637619, "messageCounter": 0, "serialNumberCtm": "0", "telemetries": [{"name": "Relative engine torque SDF", "physicalValue": 11}, {"name": "Tank Level SDF", "physicalValue": 72}, {"name": "C_EPB_STATE", "physicalValue": "2.0"}, {"name": "Vehicle speed SDF", "physicalValue": 2.21875}, {"name": "C_EPB_XACTUATOR", "physicalValue": 2.7109375}, {"name": "C_EPB_BACKUP_BATT_VOLT", "physicalValue": 13.26}, {"name": "Engine Speed SDF", "physicalValue": 1138}, {"name": "Actual engine torque SDF", "physicalValue": 6}, {"name": "Front PTO Speed SDF", "physicalValue": 0}, {"name": "Rear PTO Speed SDF", "physicalValue": 0}, {"name": "4WD status SDF", "physicalValue": null}, {"name": "DiffLock state SDF", "physicalValue": null}, {"name": "Fuel Consumption SDF", "physicalValue": 1.2}, {"name": "Intake_Manifold_Temperature", "physicalValue": null}, {"name": "Exhaust_Gas_Temperature", "physicalValue": null}, {"name": "Engine oil pressure SDF", "physicalValue": 3.6}, {"name": "Power_reduction", "physicalValue": null}, {"name": "Power_reduction_MD3", "physicalValue": null}, {"name": "Rear Lift Position SDF", "physicalValue": 97}, {"name": "DPF_SootLoadPercent", "physicalValue": 56}, {"name": "Battery voltage SDF", "physicalValue": 14.15}, {"name": "Cabin temperature SDF", "physicalValue": 27}, {"name": "AC status SDF", "physicalValue": 18}, {"name": "Urea level SDF", "physicalValue": 94.8}, {"name": "Ambient temperature SDF", "physicalValue": 21.78125}, {"name": "Oil Temperature SDF - Frutteto", "physicalValue": 61}, {"name": "Engine Coolant Temperature SDF", "physicalValue": null}, {"name": "Engine oil temperature SDF", "physicalValue": null}, {"name": "Engine Hours SDF", "physicalValue": null}], "timeStamp": "2023-08-05T09:32:48Z", "vin": "WSXFN60200LD10538"}