{"altitude": 0.0, "latitude": 44.8518118333, "longitude": 11.959316, "messageCounter": 0, "serialNumberCtm": "0", "telemetries": [{"name": "Relative engine torque SDF", "physicalValue": 68}, {"name": "Tank Level SDF", "physicalValue": 93}, {"name": "C_EPB_STATE", "physicalValue": null}, {"name": "Vehicle speed SDF", "physicalValue": 2.91406}, {"name": "C_EPB_XACTUATOR", "physicalValue": null}, {"name": "C_EPB_BACKUP_BATT_VOLT", "physicalValue": null}, {"name": "Engine Speed SDF", "physicalValue": 1680}, {"name": "Actual engine torque SDF", "physicalValue": 37}, {"name": "Front PTO Speed SDF", "physicalValue": 0}, {"name": "Rear PTO Speed SDF", "physicalValue": 846}, {"name": "4WD status SDF", "physicalValue": null}, {"name": "DiffLock state SDF", "physicalValue": null}, {"name": "Fuel Consumption SDF", "physicalValue": 8.45}, {"name": "Intake_Manifold_Temperature", "physicalValue": 31}, {"name": "Exhaust_Gas_Temperature", "physicalValue": 305}, {"name": "Engine oil pressure SDF", "physicalValue": 10.12}, {"name": "Power_reduction", "physicalValue": 99}, {"name": "Power_reduction_MD3", "physicalValue": 99}, {"name": "Rear Lift Position SDF", "physicalValue": 21}, {"name": "DPF_SootLoadPercent", "physicalValue": 47}, {"name": "Battery voltage SDF", "physicalValue": 13.85}, {"name": "Cabin temperature SDF", "physicalValue": null}, {"name": "AC status SDF", "physicalValue": null}, {"name": "Urea level SDF", "physicalValue": 44.8}, {"name": "Ambient temperature SDF", "physicalValue": 11.0625}, {"name": "Oil Temperature SDF - Frutteto", "physicalValue": 54}, {"name": "Engine Coolant Temperature SDF", "physicalValue": 80}, {"name": "Engine oil temperature SDF", "physicalValue": 83}, {"name": "Engine Hours SDF", "physicalValue": 396.75}], "timeStamp": "2023-11-29T13:22:02.376000Z", "vin": "ZKDLW702W0TD50046"}